falcano/__init__.py
falcano/attributes.py
falcano/constants.py
falcano/exceptions.py
falcano/indexes.py
falcano/model.py
falcano/paginator.py
falcano/settings.py
falcano/types.py
falcano/expressions/__init__.py
falcano/expressions/operand.py
falcano/expressions/projection.py
falcano/expressions/update.py
falcano/expressions/util.py
falcano-0.0.10.dist-info/LICENSE
falcano-0.0.10.dist-info/METADATA
falcano-0.0.10.dist-info/WHEEL
falcano-0.0.10.dist-info/top_level.txt
falcano-0.0.10.dist-info/RECORD
