Metadata-Version: 2.1
Name: falcano
Version: 0.0.10
Summary: Falcano
Home-page: https://github.com/3mcloud/falcano
Author: Eric Walker
Author-email: ewalker3@mmm.com
License: UNKNOWN
Platform: UNKNOWN
Classifier: Programming Language :: Python :: 3
Classifier: License :: OSI Approved :: BSD License
Classifier: Operating System :: OS Independent
Requires-Python: >=3.6
Requires-Dist: stringcase
Provides-Extra: dev
Requires-Dist: rsa (>=4.3) ; extra == 'dev'
Requires-Dist: PyYAML (>=5.3.1) ; extra == 'dev'
Requires-Dist: pylint (>=2.5.0) ; extra == 'dev'
Requires-Dist: pytest (>=5.4.1) ; extra == 'dev'
Requires-Dist: pytest-cov (>=2.8.1) ; extra == 'dev'
Requires-Dist: bandit (>=1.6.2) ; extra == 'dev'
Requires-Dist: safety (>=1.8.7) ; extra == 'dev'
Requires-Dist: paste ; extra == 'dev'
Requires-Dist: ptvsd ; extra == 'dev'
Requires-Dist: boto3 ; extra == 'dev'
